slimta/bounce/__init__.py
slimta/cloudstorage/__init__.py
slimta/cloudstorage/aws.py
slimta/core/__init__.py
slimta/diskstorage/__init__.py
slimta/edge/__init__.py
slimta/edge/smtp.py
slimta/edge/wsgi.py
slimta/envelope/__init__.py
slimta/http/__init__.py
slimta/http/wsgi.py
slimta/logging/__init__.py
slimta/logging/http.py
slimta/logging/log.py
slimta/logging/queuestorage.py
slimta/logging/socket.py
slimta/logging/subprocess.py
slimta/lookup/__init__.py
slimta/lookup/policy.py
slimta/lookup/drivers/__init__.py
slimta/lookup/drivers/dbapi2.py
slimta/lookup/drivers/dict.py
slimta/lookup/drivers/redis.py
slimta/lookup/drivers/regex.py
slimta/policy/__init__.py
slimta/policy/forward.py
slimta/policy/headers.py
slimta/policy/spamassassin.py
slimta/policy/split.py
slimta/queue/__init__.py
slimta/queue/dict.py
slimta/queue/proxy.py
slimta/redisstorage/__init__.py
slimta/relay/__init__.py
slimta/relay/blackhole.py
slimta/relay/http.py
slimta/relay/pipe.py
slimta/relay/pool.py
slimta/relay/smtp/__init__.py
slimta/relay/smtp/client.py
slimta/relay/smtp/lmtpclient.py
slimta/relay/smtp/mx.py
slimta/relay/smtp/static.py
slimta/smtp/__init__.py
slimta/smtp/auth.py
slimta/smtp/client.py
slimta/smtp/datareader.py
slimta/smtp/datasender.py
slimta/smtp/extensions.py
slimta/smtp/io.py
slimta/smtp/reply.py
slimta/smtp/server.py
slimta/util/__init__.py
slimta/util/bytesformat.py
slimta/util/deque.py
slimta/util/dns.py
slimta/util/dnsbl.py
slimta/util/proxyproto.py
slimta/util/ptrlookup.py
slimta/util/spf.py
slimta/util/system.py
python_slimta-5.0.5.dist-info/LICENSE.md
python_slimta-5.0.5.dist-info/METADATA
python_slimta-5.0.5.dist-info/WHEEL
python_slimta-5.0.5.dist-info/top_level.txt
python_slimta-5.0.5.dist-info/RECORD
