Metadata-Version: 2.1
Name: python-slimta
Version: 5.0.5
Summary: Lightweight, asynchronous SMTP libraries.
Home-page: http://slimta.org/
Author: Ian Good
Author-email: ian@icgood.net
License: MIT
Classifier: Development Status :: 3 - Alpha
Classifier: Topic :: Communications :: Email :: Mail Transport Agents
Classifier: Intended Audience :: Developers
Classifier: Intended Audience :: Information Technology
Classifier: License :: OSI Approved :: MIT License
Classifier: Programming Language :: Python
Classifier: Programming Language :: Python :: 3.7
Classifier: Programming Language :: Python :: 3.8
Classifier: Programming Language :: Python :: 3.9
Classifier: Programming Language :: Python :: 3.10
Classifier: Programming Language :: Python :: 3.11
License-File: LICENSE.md
Requires-Dist: gevent (>=1.1)
Requires-Dist: pysasl (>=1)
Requires-Dist: pycares (>=1)
Provides-Extra: aws
Requires-Dist: boto ; extra == 'aws'
Provides-Extra: disk
Requires-Dist: pyaio (>=0.4) ; (platform_system == "Linux") and extra == 'disk'
Provides-Extra: redis
Requires-Dist: redis ; extra == 'redis'
Provides-Extra: spf
Requires-Dist: pyspf ; extra == 'spf'
Requires-Dist: py3dns ; extra == 'spf'
